nonebot_plugin_splatoon3_nso/__init__.py
nonebot_plugin_splatoon3_nso/config.py
nonebot_plugin_splatoon3_nso/data/__init__.py
nonebot_plugin_splatoon3_nso/data/data_source.py
nonebot_plugin_splatoon3_nso/data/db_sqlite.py
nonebot_plugin_splatoon3_nso/data/transfer.py
nonebot_plugin_splatoon3_nso/data/utils.py
nonebot_plugin_splatoon3_nso/handle/__init__.py
nonebot_plugin_splatoon3_nso/handle/admin.py
nonebot_plugin_splatoon3_nso/handle/b_or_c_tools.py
nonebot_plugin_splatoon3_nso/handle/battle.py
nonebot_plugin_splatoon3_nso/handle/coop.py
nonebot_plugin_splatoon3_nso/handle/cron/__init__.py
nonebot_plugin_splatoon3_nso/handle/cron/else_cron.py
nonebot_plugin_splatoon3_nso/handle/cron/event_top.py
nonebot_plugin_splatoon3_nso/handle/cron/report.py
nonebot_plugin_splatoon3_nso/handle/cron/stat_ink.py
nonebot_plugin_splatoon3_nso/handle/cron/user_friends.py
nonebot_plugin_splatoon3_nso/handle/cron/utils.py
nonebot_plugin_splatoon3_nso/handle/cron/x_player.py
nonebot_plugin_splatoon3_nso/handle/history.py
nonebot_plugin_splatoon3_nso/handle/last.py
nonebot_plugin_splatoon3_nso/handle/login.py
nonebot_plugin_splatoon3_nso/handle/my.py
nonebot_plugin_splatoon3_nso/handle/push.py
nonebot_plugin_splatoon3_nso/handle/qq_md.py
nonebot_plugin_splatoon3_nso/handle/report.py
nonebot_plugin_splatoon3_nso/handle/screenshot.py
nonebot_plugin_splatoon3_nso/handle/send_msg.py
nonebot_plugin_splatoon3_nso/handle/top.py
nonebot_plugin_splatoon3_nso/handle/utils.py
nonebot_plugin_splatoon3_nso/resource/i18n/en-GB.json
nonebot_plugin_splatoon3_nso/resource/i18n/ja-JP.json
nonebot_plugin_splatoon3_nso/resource/i18n/ko-KR.json
nonebot_plugin_splatoon3_nso/resource/i18n/zh-CN.json
nonebot_plugin_splatoon3_nso/resource/i18n/zh-TW.json
nonebot_plugin_splatoon3_nso/resource/icons/AREA.png
nonebot_plugin_splatoon3_nso/resource/icons/BANKARA(CHALLENGE).png
nonebot_plugin_splatoon3_nso/resource/icons/BANKARA(OPEN).png
nonebot_plugin_splatoon3_nso/resource/icons/BANKARA.png
nonebot_plugin_splatoon3_nso-1.9.1.dist-info/METADATA
nonebot_plugin_splatoon3_nso-1.9.1.dist-info/WHEEL
nonebot_plugin_splatoon3_nso-1.9.1.dist-info/licenses/LICENSE
nonebot_plugin_splatoon3_nso-1.9.1.dist-info/RECORD
